fastapi_htmx/__init__.py
fastapi_htmx/htmx.py
fastapi_htmx/py.typed
fastapi_htmx-0.5.0.dist-info/LICENCE.md
fastapi_htmx-0.5.0.dist-info/METADATA
fastapi_htmx-0.5.0.dist-info/WHEEL
fastapi_htmx-0.5.0.dist-info/RECORD
